cachub/__init__.py
cachub/version.py
cachub/flask/__init__.py
cachub/flask/auth.py
cachub/flask/wsgi.py
cachub-0.0.2.dist-info/licenses/AUTHORS.rst
cachub-0.0.2.dist-info/licenses/LICENSE
cachub-0.0.2.dist-info/METADATA
cachub-0.0.2.dist-info/WHEEL
cachub-0.0.2.dist-info/top_level.txt
cachub-0.0.2.dist-info/RECORD
